[
    {
        "criteriaName": "Criteria 1",
        "criteriaId": 1
    },
    {
        "criteriaName": "Criteria 2",
        "criteriaId": 2
    },
    {
        "criteriaName": "Criteria 3",
        "criteriaId": 3
    },
    {
        "criteriaName": "Criteria 4",
        "criteriaId": 4
    },
    {
        "criteriaName": "Criteria 5",
        "criteriaId": 5
    },
    {
        "criteriaName": "Criteria 6",
        "criteriaId": 6
    },
    {
        "criteriaName": "Criteria 7",
        "criteriaId": 7
    },
    {
        "criteriaName": "Criteria 8",
        "criteriaId": 8
    },
    {
        "criteriaName": "Criteria 9",
        "criteriaId": 9
    },
    {
        "criteriaName": "Criteria 10",
        "criteriaId": 10
    }
]